gensql/__init__.py
gensql/db.py
gensql/gateway.jar
gensql-0.2.1.dist-info/METADATA
gensql-0.2.1.dist-info/WHEEL
gensql-0.2.1.dist-info/entry_points.txt
gensql-0.2.1.dist-info/licenses/LICENSE
gensql-0.2.1.dist-info/RECORD
